file/__init__.py
file/file_utils.py
irlutils/__init__.py
irlutils/file/__init__.py
irlutils/file/file_utils.py
irlutils/stats/__init__.py
irlutils/stats/tests/__init__.py
irlutils/stats/tests/proportions/__init__.py
irlutils/stats/tests/proportions/chi2_proportions.py
irlutils/url/__init__.py
irlutils/url/crawl/__init__.py
irlutils/url/crawl/analysis_utils.py
irlutils/url/crawl/blocklist_utils.py
irlutils/url/crawl/database_utils.py
irlutils/url/crawl/domain_utils.py
plot/__init__.py
plot/plotting.py
stats/__init__.py
stats/tests/__init__.py
stats/tests/proportions/__init__.py
stats/tests/proportions/chi2_proportions.py
url/__init__.py
url/crawl/__init__.py
url/crawl/analysis_utils.py
url/crawl/blocklist_utils.py
url/crawl/database_utils.py
url/crawl/domain_utils.py
irlutils-0.1.4.dist-info/LICENSE
irlutils-0.1.4.dist-info/METADATA
irlutils-0.1.4.dist-info/WHEEL
irlutils-0.1.4.dist-info/top_level.txt
irlutils-0.1.4.dist-info/RECORD
