Metadata-Version: 2.1
Name: irlutils
Version: 0.1.4
Summary: IRL Utilities
Home-page: https://github.com/uiowa-irl/uiowa-irl-utils.git
Author: The University of Iowa Internet Research Lab
Author-email: john-cook@uiowa.edu
License: UNKNOWN
Platform: UNKNOWN
Classifier: Programming Language :: Python :: 3
Classifier: License :: OSI Approved :: MIT License
Classifier: Operating System :: OS Independent
